{"Exif":{"Lat":0,"Long":0,"Date":"2024-08-20T18:11:45+08:00","Tags":{"ApertureValue":6.300000748419412,"BrightnessValue|*imagemeta.rat[int32]":"6107/1280","CreateDate":"2024:08:20 18:11:45","CustomRendered|uint16":"0","DateTimeOriginal":"2024:08:20 18:11:45","DigitalZoomRatio|*imagemeta.rat[uint32]":"1","ExposureCompensation|*imagemeta.rat[int32]":"0","ExposureTime|*imagemeta.rat[uint32]":"1/30","FNumber|*imagemeta.rat[uint32]":"63/10","FileSource|uint8":"3","FocalLengthIn35mmFormat|uint16":"94","FocalLength|*imagemeta.rat[uint32]":"63","ISO|uint16":"200","LensInfo":"28 200 2.8 5.6","LensModel":"E 28-200mm F2.8-5.6 A071","LightSource|uint16":"0","Make":"SONY","MaxApertureValue":4,"Model":"ILCE-7M4","ModifyDate":"2024:08:21 20:23:36","OffsetTime":"+02:00","OffsetTimeDigitized":"+01:00","OffsetTimeOriginal":"+01:00","RecommendedExposureIndex|uint32":"200","SceneCaptureType|uint16":"0","SceneType|uint8":"1","SensitivityType|uint16":"2","ShutterSpeedValue":0.033333323989907473,"Software":"Adobe Photoshop Lightroom Classic 13.2 (Windows)","SubSecTimeDigitized|int":"845","SubSecTimeOriginal|int":"845"}}}
